{
	"name": "Vimium C",
	"@time": "2/19/2023, 10:09:16 PM",
	"time": 1676819356398,
	"environment": {
		"extension": "1.99.97",
		"platform": "linux",
		"chromium": 110
	},
	"exclusionRules": [
		{
			"passKeys": "? ",
			"pattern": "^https?://mail\\.google\\.com/"
		},
		{
			"passKeys": "- / < > ? [ ] b d j k l ",
			"pattern": "^https?://trello\\.com/"
		},
		{
			"passKeys": "/ ",
			"pattern": "^https?://keep\\.google\\.com/"
		},
		{
			"passKeys": "/ ? ",
			"pattern": "^https?://drive\\.google\\.com/"
		},
		{
			"passKeys": "t ",
			"pattern": "^https?://github\\.com/"
		},
		{
			"passKeys": "E c s ",
			"pattern": "^https?://todomvc\\.com/"
		},
		{
			"passKeys": "t ",
			"pattern": "^https?://gitlab\\.com/"
		},
		{
			"passKeys": "<f2> ",
			"pattern": ":https://docs.google.com/"
		}
	],
	"keyLayout": 2,
	"keyMappings": [
		"#!no-check",
		"map g<tab> visitPreviousTab",
		"map glf LinkHints.activate action=\"focus\"",
		"map glh LinkHints.activate action=\"hover\"",
		"map <a-i> LinkHints.activateOpenIncognito",
		"map <a-h> previousTab",
		"map <a-l> nextTab",
		"map <c-]> passNextKey",
		"unmap r",
		"unmap x",
		"map go Vomnibar.activateInNewTab keyword=\"go\"",
		"map gh Vomnibar.activateInNewTab keyword=\"gh\"",
		""
	],
	"vimSync": true
}
